fbm/__init__.py
fbm/__version__.py
fbm/fbm.py
fbm/mbm.py
fbm-0.3.0.dist-info/LICENSE.txt
fbm-0.3.0.dist-info/METADATA
fbm-0.3.0.dist-info/WHEEL
fbm-0.3.0.dist-info/top_level.txt
fbm-0.3.0.dist-info/RECORD
